[
  {
    "typ": "IF",
    "val": "IF",
    "line": 2,
    "column": 4
  },
  {
    "typ": "ID",
    "val": "quantity",
    "line": 2,
    "column": 7
  },
  {
    "typ": "THEN",
    "val": "THEN",
    "line": 2,
    "column": 16
  },
  {
    "typ": "ID",
    "val": "total",
    "line": 3,
    "column": 8
  },
  {
    "typ": "ASSIGN",
    "val": ":=",
    "line": 3,
    "column": 14
  },
  {
    "typ": "ID",
    "val": "total",
    "line": 3,
    "column": 17
  },
  {
    "typ": "OP",
    "val": "+",
    "line": 3,
    "column": 23
  },
  {
    "typ": "ID",
    "val": "price",
    "line": 3,
    "column": 25
  },
  {
    "typ": "OP",
    "val": "*",
    "line": 3,
    "column": 31
  },
  {
    "typ": "ID",
    "val": "quantity",
    "line": 3,
    "column": 33
  },
  {
    "typ": "END",
    "val": ";",
    "line": 3,
    "column": 41
  },
  {
    "typ": "ID",
    "val": "tax",
    "line": 4,
    "column": 8
  },
  {
    "typ": "ASSIGN",
    "val": ":=",
    "line": 4,
    "column": 12
  },
  {
    "typ": "ID",
    "val": "price",
    "line": 4,
    "column": 15
  },
  {
    "typ": "OP",
    "val": "*",
    "line": 4,
    "column": 21
  },
  {
    "typ": "NUMBER",
    "val": "0.05",
    "line": 4,
    "column": 23
  },
  {
    "typ": "END",
    "val": ";",
    "line": 4,
    "column": 27
  },
  {
    "typ": "ENDIF",
    "val": "ENDIF",
    "line": 5,
    "column": 4
  },
  {
    "typ": "END",
    "val": ";",
    "line": 5,
    "column": 9
  }
]
